actions/__init__.py
actions/nadd
actions/ndel
actions/ndo
actions/ndoc
todosh_notion/__init__.py
todosh_notion/settings.py
todosh_notion/todonotion.py
todo.sh_notion-0.1.4.dist-info/AUTHORS.md
todo.sh_notion-0.1.4.dist-info/LICENSE.txt
todo.sh_notion-0.1.4.dist-info/METADATA
todo.sh_notion-0.1.4.dist-info/WHEEL
todo.sh_notion-0.1.4.dist-info/entry_points.txt
todo.sh_notion-0.1.4.dist-info/top_level.txt
todo.sh_notion-0.1.4.dist-info/RECORD
