Metadata-Version: 2.1
Name: todo.sh-notion
Version: 0.1.4
Summary: Integration between todo.sh and Notion Task Lists!
Home-page: https://github.com/Ronald-TR/todo.sh-notion
Author: Ronald Rodrigues Farias
Author-email: ronald-farias@outlook.com
License: MIT
Project-URL: Documentation, https://pyscaffold.org/
Platform: any
Classifier: Development Status :: 4 - Beta
Classifier: Programming Language :: Python
License-File: LICENSE.txt
License-File: AUTHORS.md
Requires-Dist: notion (==0.0.28)
Requires-Dist: importlib-metadata ; python_version < "3.8"
